_jsonnet.cpython-38-x86_64-linux-gnu.so
jsonnetbin-0.16.0.dist-info/RECORD
jsonnetbin-0.16.0.dist-info/WHEEL
jsonnetbin-0.16.0.dist-info/top_level.txt
jsonnetbin-0.16.0.dist-info/METADATA
jsonnetbin-0.16.0.dist-info/LICENSE
