Metadata-Version: 2.1
Name: jsonnetbin
Version: 0.16.0
Summary: An UNOFFICIAL Python interface to Jsonnet.
Home-page: https://github.com/mcovalt/jsonnetbin
Author: Matt Covalt
Author-email: mcovalt@mailbox.org
License: UNKNOWN
Platform: UNKNOWN
